[
  {
    "ContainingType": "UniversityManagmentSystem.Controllers.BlockController",
    "Method": "Delete",
    "RelativePath": "Block/DeleteBlock",
    "HttpMethod": "POST",
    "IsController": true,
    "Order": 0,
    "Parameters": [
      {
        "Name": "Id",
        "Type": "System.Int32",
        "IsRequired": false
      },
      {
        "Name": "BlockName",
        "Type": "System.String",
        "IsRequired": false
      },
      {
        "Name": "BlockCode",
        "Type": "System.String",
        "IsRequired": false
      },
      {
        "Name": "BlockDescription",
        "Type": "System.String",
        "IsRequired": false
      },
      {
        "Name": "Address",
        "Type": "System.String",
        "IsRequired": false
      },
      {
        "Name": "CampusId",
        "Type": "System.Int32",
        "IsRequired": false
      }
    ],
    "ReturnTypes": []
  },
  {
    "ContainingType": "UniversityManagmentSystem.Controllers.BlockController",
    "Method": "GetAllBlocks",
    "RelativePath": "Block/Get",
    "HttpMethod": "GET",
    "IsController": true,
    "Order": 0,
    "Parameters": [],
    "ReturnTypes": []
  },
  {
    "ContainingType": "UniversityManagmentSystem.Controllers.BlockController",
    "Method": "Post",
    "RelativePath": "Block/Post",
    "HttpMethod": "POST",
    "IsController": true,
    "Order": 0,
    "Parameters": [
      {
        "Name": "Id",
        "Type": "System.Int32",
        "IsRequired": false
      },
      {
        "Name": "BlockName",
        "Type": "System.String",
        "IsRequired": false
      },
      {
        "Name": "BlockCode",
        "Type": "System.String",
        "IsRequired": false
      },
      {
        "Name": "BlockDescription",
        "Type": "System.String",
        "IsRequired": false
      },
      {
        "Name": "Address",
        "Type": "System.String",
        "IsRequired": false
      },
      {
        "Name": "CampusId",
        "Type": "System.Int32",
        "IsRequired": false
      }
    ],
    "ReturnTypes": []
  },
  {
    "ContainingType": "UniversityManagmentSystem.Controllers.BuildingController",
    "Method": "Delete",
    "RelativePath": "Building/Delete",
    "HttpMethod": "POST",
    "IsController": true,
    "Order": 0,
    "Parameters": [
      {
        "Name": "request",
        "Type": "UniversityManagmentSystem.DTOs.RequestDTO.UniversityRequestDTO",
        "IsRequired": true
      }
    ],
    "ReturnTypes": []
  },
  {
    "ContainingType": "UniversityManagmentSystem.Controllers.BuildingController",
    "Method": "GetBuilding",
    "RelativePath": "Building/Get",
    "HttpMethod": "POST",
    "IsController": true,
    "Order": 0,
    "Parameters": [],
    "ReturnTypes": []
  },
  {
    "ContainingType": "UniversityManagmentSystem.Controllers.BuildingController",
    "Method": "AddBuilding",
    "RelativePath": "Building/Post",
    "HttpMethod": "POST",
    "IsController": true,
    "Order": 0,
    "Parameters": [
      {
        "Name": "Id",
        "Type": "System.Int32",
        "IsRequired": false
      },
      {
        "Name": "BuildingName",
        "Type": "System.String",
        "IsRequired": false
      },
      {
        "Name": "Code",
        "Type": "System.String",
        "IsRequired": false
      },
      {
        "Name": "Description",
        "Type": "System.String",
        "IsRequired": false
      },
      {
        "Name": "EstablishedIn",
        "Type": "System.DateTime",
        "IsRequired": false
      },
      {
        "Name": "Address",
        "Type": "System.String",
        "IsRequired": false
      },
      {
        "Name": "BlockId",
        "Type": "System.Int32",
        "IsRequired": false
      }
    ],
    "ReturnTypes": []
  },
  {
    "ContainingType": "UniversityManagmentSystem.Controllers.CampusController",
    "Method": "Delete",
    "RelativePath": "Campus/Delete",
    "HttpMethod": "POST",
    "IsController": true,
    "Order": 0,
    "Parameters": [
      {
        "Name": "Id",
        "Type": "System.Int32",
        "IsRequired": false
      },
      {
        "Name": "CampusName",
        "Type": "System.String",
        "IsRequired": false
      },
      {
        "Name": "Code",
        "Type": "System.String",
        "IsRequired": false
      },
      {
        "Name": "Description",
        "Type": "System.String",
        "IsRequired": false
      },
      {
        "Name": "EstablishedIn",
        "Type": "System.DateTime",
        "IsRequired": false
      },
      {
        "Name": "Address",
        "Type": "System.String",
        "IsRequired": false
      },
      {
        "Name": "UniversityId",
        "Type": "System.Int32",
        "IsRequired": false
      }
    ],
    "ReturnTypes": []
  },
  {
    "ContainingType": "UniversityManagmentSystem.Controllers.CampusController",
    "Method": "Edit",
    "RelativePath": "Campus/Edit",
    "HttpMethod": "PUT",
    "IsController": true,
    "Order": 0,
    "Parameters": [
      {
        "Name": "Id",
        "Type": "System.Int32",
        "IsRequired": false
      },
      {
        "Name": "CampusName",
        "Type": "System.String",
        "IsRequired": false
      },
      {
        "Name": "Code",
        "Type": "System.String",
        "IsRequired": false
      },
      {
        "Name": "Description",
        "Type": "System.String",
        "IsRequired": false
      },
      {
        "Name": "EstablishedIn",
        "Type": "System.DateTime",
        "IsRequired": false
      },
      {
        "Name": "Address",
        "Type": "System.String",
        "IsRequired": false
      },
      {
        "Name": "UniversityId",
        "Type": "System.Int32",
        "IsRequired": false
      }
    ],
    "ReturnTypes": []
  },
  {
    "ContainingType": "UniversityManagmentSystem.Controllers.CampusController",
    "Method": "GetCampus",
    "RelativePath": "Campus/Get",
    "HttpMethod": "POST",
    "IsController": true,
    "Order": 0,
    "Parameters": [],
    "ReturnTypes": []
  },
  {
    "ContainingType": "UniversityManagmentSystem.Controllers.CampusController",
    "Method": "AddBuilding",
    "RelativePath": "Campus/Post",
    "HttpMethod": "POST",
    "IsController": true,
    "Order": 0,
    "Parameters": [
      {
        "Name": "Id",
        "Type": "System.Int32",
        "IsRequired": false
      },
      {
        "Name": "CampusName",
        "Type": "System.String",
        "IsRequired": false
      },
      {
        "Name": "Code",
        "Type": "System.String",
        "IsRequired": false
      },
      {
        "Name": "Description",
        "Type": "System.String",
        "IsRequired": false
      },
      {
        "Name": "EstablishedIn",
        "Type": "System.DateTime",
        "IsRequired": false
      },
      {
        "Name": "Address",
        "Type": "System.String",
        "IsRequired": false
      },
      {
        "Name": "UniversityId",
        "Type": "System.Int32",
        "IsRequired": false
      }
    ],
    "ReturnTypes": []
  },
  {
    "ContainingType": "UniversityManagmentSystem.Controllers.CLOController",
    "Method": "Delete",
    "RelativePath": "CLO/DeleteCLO",
    "HttpMethod": "POST",
    "IsController": true,
    "Order": 0,
    "Parameters": [
      {
        "Name": "Id",
        "Type": "System.Int32",
        "IsRequired": false
      },
      {
        "Name": "Description",
        "Type": "System.String",
        "IsRequired": false
      },
      {
        "Name": "Code",
        "Type": "System.String",
        "IsRequired": false
      },
      {
        "Name": "SubjectTypeId",
        "Type": "System.Int32",
        "IsRequired": false
      },
      {
        "Name": "LearningLevelId",
        "Type": "System.Int32",
        "IsRequired": false
      }
    ],
    "ReturnTypes": []
  },
  {
    "ContainingType": "UniversityManagmentSystem.Controllers.CLOController",
    "Method": "GetAllCLOs",
    "RelativePath": "CLO/Get",
    "HttpMethod": "GET",
    "IsController": true,
    "Order": 0,
    "Parameters": [],
    "ReturnTypes": []
  },
  {
    "ContainingType": "UniversityManagmentSystem.Controllers.CLOController",
    "Method": "Post",
    "RelativePath": "CLO/Post",
    "HttpMethod": "POST",
    "IsController": true,
    "Order": 0,
    "Parameters": [
      {
        "Name": "Id",
        "Type": "System.Int32",
        "IsRequired": false
      },
      {
        "Name": "Description",
        "Type": "System.String",
        "IsRequired": false
      },
      {
        "Name": "Code",
        "Type": "System.String",
        "IsRequired": false
      },
      {
        "Name": "SubjectTypeId",
        "Type": "System.Int32",
        "IsRequired": false
      },
      {
        "Name": "LearningLevelId",
        "Type": "System.Int32",
        "IsRequired": false
      }
    ],
    "ReturnTypes": []
  },
  {
    "ContainingType": "UniversityManagmentSystem.Controllers.CloToSubjectController",
    "Method": "Delete",
    "RelativePath": "CloToSubject/DeleteCloToSubject",
    "HttpMethod": "POST",
    "IsController": true,
    "Order": 0,
    "Parameters": [
      {
        "Name": "Id",
        "Type": "System.Int32",
        "IsRequired": false
      },
      {
        "Name": "CloId",
        "Type": "System.Int32",
        "IsRequired": false
      },
      {
        "Name": "SubjectId",
        "Type": "System.Int32",
        "IsRequired": false
      },
      {
        "Name": "ProgramSessionId",
        "Type": "System.Int32",
        "IsRequired": false
      }
    ],
    "ReturnTypes": []
  },
  {
    "ContainingType": "UniversityManagmentSystem.Controllers.CloToSubjectController",
    "Method": "GetAllCloToSubjects",
    "RelativePath": "CloToSubject/Get",
    "HttpMethod": "GET",
    "IsController": true,
    "Order": 0,
    "Parameters": [],
    "ReturnTypes": []
  },
  {
    "ContainingType": "UniversityManagmentSystem.Controllers.CloToSubjectController",
    "Method": "Post",
    "RelativePath": "CloToSubject/Post",
    "HttpMethod": "POST",
    "IsController": true,
    "Order": 0,
    "Parameters": [
      {
        "Name": "Id",
        "Type": "System.Int32",
        "IsRequired": false
      },
      {
        "Name": "CloId",
        "Type": "System.Int32",
        "IsRequired": false
      },
      {
        "Name": "SubjectId",
        "Type": "System.Int32",
        "IsRequired": false
      },
      {
        "Name": "ProgramSessionId",
        "Type": "System.Int32",
        "IsRequired": false
      }
    ],
    "ReturnTypes": []
  },
  {
    "ContainingType": "UniversityManagmentSystem.Controllers.CourseSchemeController",
    "Method": "Delete",
    "RelativePath": "CourseScheme/DeleteCourseScheme",
    "HttpMethod": "POST",
    "IsController": true,
    "Order": 0,
    "Parameters": [
      {
        "Name": "request",
        "Type": "UniversityManagmentSystem.DTOs.RequestDTO.CourseSchemeRequestDTO",
        "IsRequired": true
      }
    ],
    "ReturnTypes": []
  },
  {
    "ContainingType": "UniversityManagmentSystem.Controllers.CourseSchemeController",
    "Method": "GetAllCourseSchemes",
    "RelativePath": "CourseScheme/Get",
    "HttpMethod": "GET",
    "IsController": true,
    "Order": 0,
    "Parameters": [],
    "ReturnTypes": []
  },
  {
    "ContainingType": "UniversityManagmentSystem.Controllers.CourseSchemeController",
    "Method": "Post",
    "RelativePath": "CourseScheme/Post",
    "HttpMethod": "POST",
    "IsController": true,
    "Order": 0,
    "Parameters": [
      {
        "Name": "Id",
        "Type": "System.Int32",
        "IsRequired": false
      },
      {
        "Name": "ProgramSessionId",
        "Type": "System.Int32",
        "IsRequired": false
      },
      {
        "Name": "DegreeProgramId",
        "Type": "System.Int32",
        "IsRequired": false
      },
      {
        "Name": "SubjectTypeId",
        "Type": "System.Int32",
        "IsRequired": false
      },
      {
        "Name": "SubjectId",
        "Type": "System.Int32",
        "IsRequired": false
      },
      {
        "Name": "SemesterId",
        "Type": "System.Int32",
        "IsRequired": false
      }
    ],
    "ReturnTypes": []
  },
  {
    "ContainingType": "UniversityManagmentSystem.Controllers.DegreeLevelController",
    "Method": "Post",
    "RelativePath": "DegreeLevel/DegreeLevel",
    "HttpMethod": "POST",
    "IsController": true,
    "Order": 0,
    "Parameters": [
      {
        "Name": "Id",
        "Type": "System.Int32",
        "IsRequired": false
      },
      {
        "Name": "DegreeLevelName",
        "Type": "System.String",
        "IsRequired": false
      },
      {
        "Name": "Description",
        "Type": "System.String",
        "IsRequired": false
      },
      {
        "Name": "Code",
        "Type": "System.String",
        "IsRequired": false
      }
    ],
    "ReturnTypes": []
  },
  {
    "ContainingType": "UniversityManagmentSystem.Controllers.DegreeLevelController",
    "Method": "RemoveDegreeLevel",
    "RelativePath": "DegreeLevel/DegreeLevel/{Id}",
    "HttpMethod": "POST",
    "IsController": true,
    "Order": 0,
    "Parameters": [
      {
        "Name": "Id",
        "Type": "System.Int32",
        "IsRequired": false
      },
      {
        "Name": "DegreeLevelName",
        "Type": "System.String",
        "IsRequired": false
      },
      {
        "Name": "Description",
        "Type": "System.String",
        "IsRequired": false
      },
      {
        "Name": "Code",
        "Type": "System.String",
        "IsRequired": false
      },
      {
        "Name": "Id",
        "Type": "",
        "IsRequired": true
      }
    ],
    "ReturnTypes": []
  },
  {
    "ContainingType": "UniversityManagmentSystem.Controllers.DegreeLevelController",
    "Method": "GetAllDegreeLevels",
    "RelativePath": "DegreeLevel/DegreeLevels",
    "HttpMethod": "GET",
    "IsController": true,
    "Order": 0,
    "Parameters": [],
    "ReturnTypes": []
  },
  {
    "ContainingType": "UniversityManagmentSystem.Controllers.DegreeProgramController",
    "Method": "DeleteDegProgram",
    "RelativePath": "DegreeProgram/Delete",
    "HttpMethod": "POST",
    "IsController": true,
    "Order": 0,
    "Parameters": [
      {
        "Name": "Id",
        "Type": "System.Nullable\u00601[[System.Int32, System.Private.CoreLib, Version=8.0.0.0, Culture=neutral, PublicKeyToken=7cec85d7bea7798e]]",
        "IsRequired": false
      }
    ],
    "ReturnTypes": []
  },
  {
    "ContainingType": "UniversityManagmentSystem.Controllers.DegreeProgramController",
    "Method": "AddDegreeProgram",
    "RelativePath": "DegreeProgram/Get",
    "HttpMethod": "POST",
    "IsController": true,
    "Order": 0,
    "Parameters": [
      {
        "Name": "request",
        "Type": "UniversityManagmentSystem.DTOs.RequestDTO.DegreeProgramRequestDTO",
        "IsRequired": true
      }
    ],
    "ReturnTypes": []
  },
  {
    "ContainingType": "UniversityManagmentSystem.Controllers.RoomController",
    "Method": "Delete",
    "RelativePath": "Delete",
    "HttpMethod": "POST",
    "IsController": true,
    "Order": 0,
    "Parameters": [
      {
        "Name": "Id",
        "Type": "System.Int32",
        "IsRequired": false
      },
      {
        "Name": "RoomName",
        "Type": "System.String",
        "IsRequired": false
      },
      {
        "Name": "Code",
        "Type": "System.String",
        "IsRequired": false
      },
      {
        "Name": "Description",
        "Type": "System.String",
        "IsRequired": false
      },
      {
        "Name": "EstablishedIn",
        "Type": "System.DateTime",
        "IsRequired": false
      },
      {
        "Name": "FloorId",
        "Type": "System.Int32",
        "IsRequired": false
      }
    ],
    "ReturnTypes": []
  },
  {
    "ContainingType": "UniversityManagmentSystem.Controllers.DepartmentController",
    "Method": "Delete",
    "RelativePath": "Department/DeleteDepartment",
    "HttpMethod": "POST",
    "IsController": true,
    "Order": 0,
    "Parameters": [
      {
        "Name": "Id",
        "Type": "System.Int32",
        "IsRequired": false
      },
      {
        "Name": "DepartmentName",
        "Type": "System.String",
        "IsRequired": false
      },
      {
        "Name": "Description",
        "Type": "System.String",
        "IsRequired": false
      },
      {
        "Name": "Code",
        "Type": "System.String",
        "IsRequired": false
      },
      {
        "Name": "InstituteId",
        "Type": "System.Int32",
        "IsRequired": false
      }
    ],
    "ReturnTypes": []
  },
  {
    "ContainingType": "UniversityManagmentSystem.Controllers.DepartmentController",
    "Method": "GetAllDepartments",
    "RelativePath": "Department/Get",
    "HttpMethod": "GET",
    "IsController": true,
    "Order": 0,
    "Parameters": [],
    "ReturnTypes": []
  },
  {
    "ContainingType": "UniversityManagmentSystem.Controllers.DepartmentController",
    "Method": "Post",
    "RelativePath": "Department/Post",
    "HttpMethod": "POST",
    "IsController": true,
    "Order": 0,
    "Parameters": [
      {
        "Name": "Id",
        "Type": "System.Int32",
        "IsRequired": false
      },
      {
        "Name": "DepartmentName",
        "Type": "System.String",
        "IsRequired": false
      },
      {
        "Name": "Description",
        "Type": "System.String",
        "IsRequired": false
      },
      {
        "Name": "Code",
        "Type": "System.String",
        "IsRequired": false
      },
      {
        "Name": "InstituteId",
        "Type": "System.Int32",
        "IsRequired": false
      }
    ],
    "ReturnTypes": []
  },
  {
    "ContainingType": "UniversityManagmentSystem.Controllers.DesignationController",
    "Method": "Post",
    "RelativePath": "Designation/Designation",
    "HttpMethod": "POST",
    "IsController": true,
    "Order": 0,
    "Parameters": [
      {
        "Name": "Id",
        "Type": "System.Int32",
        "IsRequired": false
      },
      {
        "Name": "DesignationName",
        "Type": "System.String",
        "IsRequired": false
      },
      {
        "Name": "Description",
        "Type": "System.String",
        "IsRequired": false
      },
      {
        "Name": "Code",
        "Type": "System.String",
        "IsRequired": false
      }
    ],
    "ReturnTypes": []
  },
  {
    "ContainingType": "UniversityManagmentSystem.Controllers.DesignationController",
    "Method": "Delete",
    "RelativePath": "Designation/Designation Delete/{id}",
    "HttpMethod": "POST",
    "IsController": true,
    "Order": 0,
    "Parameters": [
      {
        "Name": "Id",
        "Type": "System.Int32",
        "IsRequired": false
      },
      {
        "Name": "DesignationName",
        "Type": "System.String",
        "IsRequired": false
      },
      {
        "Name": "Description",
        "Type": "System.String",
        "IsRequired": false
      },
      {
        "Name": "Code",
        "Type": "System.String",
        "IsRequired": false
      },
      {
        "Name": "id",
        "Type": "",
        "IsRequired": true
      }
    ],
    "ReturnTypes": []
  },
  {
    "ContainingType": "UniversityManagmentSystem.Controllers.DesignationController",
    "Method": "GetAll",
    "RelativePath": "Designation/Designation Get All Data",
    "HttpMethod": "GET",
    "IsController": true,
    "Order": 0,
    "Parameters": [],
    "ReturnTypes": []
  },
  {
    "ContainingType": "UniversityManagmentSystem.Controllers.FacultyController",
    "Method": "Post",
    "RelativePath": "Faculty/Faculty",
    "HttpMethod": "POST",
    "IsController": true,
    "Order": 0,
    "Parameters": [
      {
        "Name": "Id",
        "Type": "System.Int32",
        "IsRequired": false
      },
      {
        "Name": "FacultyName",
        "Type": "System.String",
        "IsRequired": false
      },
      {
        "Name": "Description",
        "Type": "System.String",
        "IsRequired": false
      },
      {
        "Name": "Code",
        "Type": "System.String",
        "IsRequired": false
      },
      {
        "Name": "EstablishedIn",
        "Type": "System.DateTime",
        "IsRequired": false
      }
    ],
    "ReturnTypes": []
  },
  {
    "ContainingType": "UniversityManagmentSystem.Controllers.FacultyController",
    "Method": "GetAll",
    "RelativePath": "Faculty/Faculty",
    "HttpMethod": "GET",
    "IsController": true,
    "Order": 0,
    "Parameters": [],
    "ReturnTypes": []
  },
  {
    "ContainingType": "UniversityManagmentSystem.Controllers.FacultyController",
    "Method": "Delete",
    "RelativePath": "Faculty/Faculty/{id}",
    "HttpMethod": "DELETE",
    "IsController": true,
    "Order": 0,
    "Parameters": [
      {
        "Name": "Id",
        "Type": "System.Int32",
        "IsRequired": false
      },
      {
        "Name": "FacultyName",
        "Type": "System.String",
        "IsRequired": false
      },
      {
        "Name": "Description",
        "Type": "System.String",
        "IsRequired": false
      },
      {
        "Name": "Code",
        "Type": "System.String",
        "IsRequired": false
      },
      {
        "Name": "EstablishedIn",
        "Type": "System.DateTime",
        "IsRequired": false
      },
      {
        "Name": "id",
        "Type": "",
        "IsRequired": true
      }
    ],
    "ReturnTypes": []
  },
  {
    "ContainingType": "UniversityManagmentSystem.Controllers.FacultyCampusController",
    "Method": "Delete",
    "RelativePath": "FacultyCampus/DeleteFacultyCampus",
    "HttpMethod": "POST",
    "IsController": true,
    "Order": 0,
    "Parameters": [
      {
        "Name": "Id",
        "Type": "System.Int32",
        "IsRequired": false
      },
      {
        "Name": "FacultyId",
        "Type": "System.Int32",
        "IsRequired": false
      },
      {
        "Name": "CampusId",
        "Type": "System.Int32",
        "IsRequired": false
      }
    ],
    "ReturnTypes": []
  },
  {
    "ContainingType": "UniversityManagmentSystem.Controllers.FacultyCampusController",
    "Method": "GetAllFacultyCampuses",
    "RelativePath": "FacultyCampus/Get",
    "HttpMethod": "GET",
    "IsController": true,
    "Order": 0,
    "Parameters": [],
    "ReturnTypes": []
  },
  {
    "ContainingType": "UniversityManagmentSystem.Controllers.FacultyCampusController",
    "Method": "Post",
    "RelativePath": "FacultyCampus/Post",
    "HttpMethod": "POST",
    "IsController": true,
    "Order": 0,
    "Parameters": [
      {
        "Name": "Id",
        "Type": "System.Int32",
        "IsRequired": false
      },
      {
        "Name": "FacultyId",
        "Type": "System.Int32",
        "IsRequired": false
      },
      {
        "Name": "CampusId",
        "Type": "System.Int32",
        "IsRequired": false
      }
    ],
    "ReturnTypes": []
  },
  {
    "ContainingType": "UniversityManagmentSystem.Controllers.FloorController",
    "Method": "DeleteFloor",
    "RelativePath": "Floor/Delete",
    "HttpMethod": "POST",
    "IsController": true,
    "Order": 0,
    "Parameters": [
      {
        "Name": "request",
        "Type": "UniversityManagmentSystem.DTOs.RequestDTO.FloorRequestDTO",
        "IsRequired": true
      }
    ],
    "ReturnTypes": []
  },
  {
    "ContainingType": "UniversityManagmentSystem.Controllers.FloorController",
    "Method": "GetAllFloor",
    "RelativePath": "Floor/Get",
    "HttpMethod": "GET",
    "IsController": true,
    "Order": 0,
    "Parameters": [],
    "ReturnTypes": []
  },
  {
    "ContainingType": "UniversityManagmentSystem.Controllers.FloorController",
    "Method": "Post",
    "RelativePath": "Floor/Post",
    "HttpMethod": "POST",
    "IsController": true,
    "Order": 0,
    "Parameters": [
      {
        "Name": "Id",
        "Type": "System.Int32",
        "IsRequired": false
      },
      {
        "Name": "FloorName",
        "Type": "System.String",
        "IsRequired": false
      },
      {
        "Name": "Code",
        "Type": "System.String",
        "IsRequired": false
      },
      {
        "Name": "Description",
        "Type": "System.String",
        "IsRequired": false
      },
      {
        "Name": "EstablishedIn",
        "Type": "System.DateTime",
        "IsRequired": false
      },
      {
        "Name": "BuildingId",
        "Type": "System.Int32",
        "IsRequired": false
      }
    ],
    "ReturnTypes": []
  },
  {
    "ContainingType": "UniversityManagmentSystem.Controllers.RoomController",
    "Method": "Post",
    "RelativePath": "Get",
    "HttpMethod": "POST",
    "IsController": true,
    "Order": 0,
    "Parameters": [
      {
        "Name": "Id",
        "Type": "System.Int32",
        "IsRequired": false
      },
      {
        "Name": "RoomName",
        "Type": "System.String",
        "IsRequired": false
      },
      {
        "Name": "Code",
        "Type": "System.String",
        "IsRequired": false
      },
      {
        "Name": "Description",
        "Type": "System.String",
        "IsRequired": false
      },
      {
        "Name": "EstablishedIn",
        "Type": "System.DateTime",
        "IsRequired": false
      },
      {
        "Name": "FloorId",
        "Type": "System.Int32",
        "IsRequired": false
      }
    ],
    "ReturnTypes": []
  },
  {
    "ContainingType": "UniversityManagmentSystem.Controllers.RoomController",
    "Method": "GetAllRooms",
    "RelativePath": "GetAll",
    "HttpMethod": "GET",
    "IsController": true,
    "Order": 0,
    "Parameters": [],
    "ReturnTypes": []
  },
  {
    "ContainingType": "UniversityManagmentSystem.Controllers.InstituteController",
    "Method": "Delete",
    "RelativePath": "Institute/DeleteInstitute",
    "HttpMethod": "POST",
    "IsController": true,
    "Order": 0,
    "Parameters": [
      {
        "Name": "Id",
        "Type": "System.Int32",
        "IsRequired": false
      },
      {
        "Name": "InstituteName",
        "Type": "System.String",
        "IsRequired": false
      },
      {
        "Name": "Description",
        "Type": "System.String",
        "IsRequired": false
      },
      {
        "Name": "EstablishIn",
        "Type": "System.DateTime",
        "IsRequired": false
      },
      {
        "Name": "Code",
        "Type": "System.String",
        "IsRequired": false
      },
      {
        "Name": "FacultyCampusId",
        "Type": "System.Int32",
        "IsRequired": false
      }
    ],
    "ReturnTypes": []
  },
  {
    "ContainingType": "UniversityManagmentSystem.Controllers.InstituteController",
    "Method": "GetAllInstitutes",
    "RelativePath": "Institute/Get",
    "HttpMethod": "GET",
    "IsController": true,
    "Order": 0,
    "Parameters": [],
    "ReturnTypes": []
  },
  {
    "ContainingType": "UniversityManagmentSystem.Controllers.InstituteController",
    "Method": "Post",
    "RelativePath": "Institute/Post",
    "HttpMethod": "POST",
    "IsController": true,
    "Order": 0,
    "Parameters": [
      {
        "Name": "Id",
        "Type": "System.Int32",
        "IsRequired": false
      },
      {
        "Name": "InstituteName",
        "Type": "System.String",
        "IsRequired": false
      },
      {
        "Name": "Description",
        "Type": "System.String",
        "IsRequired": false
      },
      {
        "Name": "EstablishIn",
        "Type": "System.DateTime",
        "IsRequired": false
      },
      {
        "Name": "Code",
        "Type": "System.String",
        "IsRequired": false
      },
      {
        "Name": "FacultyCampusId",
        "Type": "System.Int32",
        "IsRequired": false
      }
    ],
    "ReturnTypes": []
  },
  {
    "ContainingType": "UniversityManagmentSystem.Controllers.LearningLevelController",
    "Method": "Delete",
    "RelativePath": "LearningLevel/DeleteLearningLevel",
    "HttpMethod": "POST",
    "IsController": true,
    "Order": 0,
    "Parameters": [
      {
        "Name": "request",
        "Type": "UniversityManagmentSystem.DTOs.RequestDTO.LearningLevelRequestDTO",
        "IsRequired": true
      }
    ],
    "ReturnTypes": []
  },
  {
    "ContainingType": "UniversityManagmentSystem.Controllers.LearningLevelController",
    "Method": "GetAllLearningLevels",
    "RelativePath": "LearningLevel/Get",
    "HttpMethod": "GET",
    "IsController": true,
    "Order": 0,
    "Parameters": [],
    "ReturnTypes": []
  },
  {
    "ContainingType": "UniversityManagmentSystem.Controllers.LearningLevelController",
    "Method": "Post",
    "RelativePath": "LearningLevel/Post",
    "HttpMethod": "POST",
    "IsController": true,
    "Order": 0,
    "Parameters": [
      {
        "Name": "Id",
        "Type": "System.Int32",
        "IsRequired": false
      },
      {
        "Name": "LearningLevelName",
        "Type": "System.String",
        "IsRequired": false
      },
      {
        "Name": "Description",
        "Type": "System.String",
        "IsRequired": false
      },
      {
        "Name": "Code",
        "Type": "System.String",
        "IsRequired": false
      }
    ],
    "ReturnTypes": []
  },
  {
    "ContainingType": "UniversityManagmentSystem.Controllers.PEOController",
    "Method": "Delete",
    "RelativePath": "PEO/DeletePEO",
    "HttpMethod": "POST",
    "IsController": true,
    "Order": 0,
    "Parameters": [
      {
        "Name": "Id",
        "Type": "System.Int32",
        "IsRequired": false
      },
      {
        "Name": "PEOName",
        "Type": "System.String",
        "IsRequired": false
      },
      {
        "Name": "Description",
        "Type": "System.String",
        "IsRequired": false
      },
      {
        "Name": "Code",
        "Type": "System.String",
        "IsRequired": false
      },
      {
        "Name": "DegreeProgramId",
        "Type": "System.Int32",
        "IsRequired": false
      }
    ],
    "ReturnTypes": []
  },
  {
    "ContainingType": "UniversityManagmentSystem.Controllers.PEOController",
    "Method": "GetAllPEOs",
    "RelativePath": "PEO/Get",
    "HttpMethod": "GET",
    "IsController": true,
    "Order": 0,
    "Parameters": [],
    "ReturnTypes": []
  },
  {
    "ContainingType": "UniversityManagmentSystem.Controllers.PEOController",
    "Method": "Post",
    "RelativePath": "PEO/Post",
    "HttpMethod": "POST",
    "IsController": true,
    "Order": 0,
    "Parameters": [
      {
        "Name": "Id",
        "Type": "System.Int32",
        "IsRequired": false
      },
      {
        "Name": "PEOName",
        "Type": "System.String",
        "IsRequired": false
      },
      {
        "Name": "Description",
        "Type": "System.String",
        "IsRequired": false
      },
      {
        "Name": "Code",
        "Type": "System.String",
        "IsRequired": false
      },
      {
        "Name": "DegreeProgramId",
        "Type": "System.Int32",
        "IsRequired": false
      }
    ],
    "ReturnTypes": []
  },
  {
    "ContainingType": "UniversityManagmentSystem.Controllers.PeoToPloController",
    "Method": "Delete",
    "RelativePath": "PeoToPlo/DeletePeoToPlo",
    "HttpMethod": "POST",
    "IsController": true,
    "Order": 0,
    "Parameters": [
      {
        "Name": "Id",
        "Type": "System.Int32",
        "IsRequired": false
      },
      {
        "Name": "PeoId",
        "Type": "System.Int32",
        "IsRequired": false
      },
      {
        "Name": "PloId",
        "Type": "System.Int32",
        "IsRequired": false
      },
      {
        "Name": "Weightage",
        "Type": "System.String",
        "IsRequired": false
      }
    ],
    "ReturnTypes": []
  },
  {
    "ContainingType": "UniversityManagmentSystem.Controllers.PeoToPloController",
    "Method": "GetAllPeoToPlos",
    "RelativePath": "PeoToPlo/Get",
    "HttpMethod": "GET",
    "IsController": true,
    "Order": 0,
    "Parameters": [],
    "ReturnTypes": []
  },
  {
    "ContainingType": "UniversityManagmentSystem.Controllers.PeoToPloController",
    "Method": "Post",
    "RelativePath": "PeoToPlo/Post",
    "HttpMethod": "POST",
    "IsController": true,
    "Order": 0,
    "Parameters": [
      {
        "Name": "Id",
        "Type": "System.Int32",
        "IsRequired": false
      },
      {
        "Name": "PeoId",
        "Type": "System.Int32",
        "IsRequired": false
      },
      {
        "Name": "PloId",
        "Type": "System.Int32",
        "IsRequired": false
      },
      {
        "Name": "Weightage",
        "Type": "System.String",
        "IsRequired": false
      }
    ],
    "ReturnTypes": []
  },
  {
    "ContainingType": "UniversityManagmentSystem.Controllers.PLOController",
    "Method": "Delete",
    "RelativePath": "PLO/DeletePLO",
    "HttpMethod": "POST",
    "IsController": true,
    "Order": 0,
    "Parameters": [
      {
        "Name": "Id",
        "Type": "System.Int32",
        "IsRequired": false
      },
      {
        "Name": "PLOName",
        "Type": "System.String",
        "IsRequired": false
      },
      {
        "Name": "Description",
        "Type": "System.String",
        "IsRequired": false
      },
      {
        "Name": "Code",
        "Type": "System.String",
        "IsRequired": false
      },
      {
        "Name": "DegreeProgramId",
        "Type": "System.Int32",
        "IsRequired": false
      }
    ],
    "ReturnTypes": []
  },
  {
    "ContainingType": "UniversityManagmentSystem.Controllers.PLOController",
    "Method": "GetAllPLOs",
    "RelativePath": "PLO/Get",
    "HttpMethod": "GET",
    "IsController": true,
    "Order": 0,
    "Parameters": [],
    "ReturnTypes": []
  },
  {
    "ContainingType": "UniversityManagmentSystem.Controllers.PLOController",
    "Method": "Post",
    "RelativePath": "PLO/Post",
    "HttpMethod": "POST",
    "IsController": true,
    "Order": 0,
    "Parameters": [
      {
        "Name": "Id",
        "Type": "System.Int32",
        "IsRequired": false
      },
      {
        "Name": "PLOName",
        "Type": "System.String",
        "IsRequired": false
      },
      {
        "Name": "Description",
        "Type": "System.String",
        "IsRequired": false
      },
      {
        "Name": "Code",
        "Type": "System.String",
        "IsRequired": false
      },
      {
        "Name": "DegreeProgramId",
        "Type": "System.Int32",
        "IsRequired": false
      }
    ],
    "ReturnTypes": []
  },
  {
    "ContainingType": "UniversityManagmentSystem.Controllers.PloToCloController",
    "Method": "Delete",
    "RelativePath": "PloToClo/DeletePloToClo",
    "HttpMethod": "POST",
    "IsController": true,
    "Order": 0,
    "Parameters": [
      {
        "Name": "Id",
        "Type": "System.Int32",
        "IsRequired": false
      },
      {
        "Name": "PloId",
        "Type": "System.Int32",
        "IsRequired": false
      },
      {
        "Name": "CloId",
        "Type": "System.Int32",
        "IsRequired": false
      },
      {
        "Name": "Weightage",
        "Type": "System.String",
        "IsRequired": false
      }
    ],
    "ReturnTypes": []
  },
  {
    "ContainingType": "UniversityManagmentSystem.Controllers.PloToCloController",
    "Method": "GetAllPloToClos",
    "RelativePath": "PloToClo/Get",
    "HttpMethod": "GET",
    "IsController": true,
    "Order": 0,
    "Parameters": [],
    "ReturnTypes": []
  },
  {
    "ContainingType": "UniversityManagmentSystem.Controllers.PloToCloController",
    "Method": "Post",
    "RelativePath": "PloToClo/Post",
    "HttpMethod": "POST",
    "IsController": true,
    "Order": 0,
    "Parameters": [
      {
        "Name": "Id",
        "Type": "System.Int32",
        "IsRequired": false
      },
      {
        "Name": "PloId",
        "Type": "System.Int32",
        "IsRequired": false
      },
      {
        "Name": "CloId",
        "Type": "System.Int32",
        "IsRequired": false
      },
      {
        "Name": "Weightage",
        "Type": "System.String",
        "IsRequired": false
      }
    ],
    "ReturnTypes": []
  },
  {
    "ContainingType": "UniversityManagmentSystem.Controllers.ProgramSessionController",
    "Method": "RemoveProgramSession",
    "RelativePath": "ProgramSession/ delete",
    "HttpMethod": "POST",
    "IsController": true,
    "Order": 0,
    "Parameters": [
      {
        "Name": "Id",
        "Type": "System.Int32",
        "IsRequired": false
      },
      {
        "Name": "SessionName",
        "Type": "System.String",
        "IsRequired": false
      },
      {
        "Name": "Code",
        "Type": "System.String",
        "IsRequired": false
      },
      {
        "Name": "Description",
        "Type": "System.String",
        "IsRequired": false
      }
    ],
    "ReturnTypes": []
  },
  {
    "ContainingType": "UniversityManagmentSystem.Controllers.ProgramSessionController",
    "Method": "PostProgramSession",
    "RelativePath": "ProgramSession/ProgramSession",
    "HttpMethod": "POST",
    "IsController": true,
    "Order": 0,
    "Parameters": [
      {
        "Name": "Id",
        "Type": "System.Int32",
        "IsRequired": false
      },
      {
        "Name": "SessionName",
        "Type": "System.String",
        "IsRequired": false
      },
      {
        "Name": "Code",
        "Type": "System.String",
        "IsRequired": false
      },
      {
        "Name": "Description",
        "Type": "System.String",
        "IsRequired": false
      }
    ],
    "ReturnTypes": []
  },
  {
    "ContainingType": "UniversityManagmentSystem.Controllers.ProgramSessionController",
    "Method": "GetAllProgramSession",
    "RelativePath": "ProgramSession/ProgramSessionGet",
    "HttpMethod": "POST",
    "IsController": true,
    "Order": 0,
    "Parameters": [],
    "ReturnTypes": []
  },
  {
    "ContainingType": "UniversityManagmentSystem.Controllers.RoomFeatureController",
    "Method": "RemoveRoomFeature",
    "RelativePath": "RoomFeature/Delete/{Id}",
    "HttpMethod": "POST",
    "IsController": true,
    "Order": 0,
    "Parameters": [
      {
        "Name": "Id",
        "Type": "System.Int32",
        "IsRequired": false
      },
      {
        "Name": "SessionName",
        "Type": "System.String",
        "IsRequired": false
      },
      {
        "Name": "Code",
        "Type": "System.String",
        "IsRequired": false
      },
      {
        "Name": "Description",
        "Type": "System.String",
        "IsRequired": false
      },
      {
        "Name": "Id",
        "Type": "",
        "IsRequired": true
      }
    ],
    "ReturnTypes": []
  },
  {
    "ContainingType": "UniversityManagmentSystem.Controllers.RoomFeatureController",
    "Method": "Post",
    "RelativePath": "RoomFeature/RoomFeature",
    "HttpMethod": "POST",
    "IsController": true,
    "Order": 0,
    "Parameters": [
      {
        "Name": "Id",
        "Type": "System.Int32",
        "IsRequired": false
      },
      {
        "Name": "RoomFeatureName",
        "Type": "System.String",
        "IsRequired": false
      },
      {
        "Name": "Code",
        "Type": "System.String",
        "IsRequired": false
      },
      {
        "Name": "Description",
        "Type": "System.String",
        "IsRequired": false
      }
    ],
    "ReturnTypes": []
  },
  {
    "ContainingType": "UniversityManagmentSystem.Controllers.RoomFeatureController",
    "Method": "GetAllRoomFeature",
    "RelativePath": "RoomFeature/RoomFeature Get",
    "HttpMethod": "GET",
    "IsController": true,
    "Order": 0,
    "Parameters": [],
    "ReturnTypes": []
  },
  {
    "ContainingType": "UniversityManagmentSystem.Controllers.RoomFeatureAllocationController",
    "Method": "DeleteRoomFeatureAllocation",
    "RelativePath": "RoomFeatureAllocation/Delete",
    "HttpMethod": "POST",
    "IsController": true,
    "Order": 0,
    "Parameters": [
      {
        "Name": "request",
        "Type": "UniversityManagmentSystem.DTOs.RequestDTO.RoomFeatureAllocationRequestDTO",
        "IsRequired": true
      }
    ],
    "ReturnTypes": []
  },
  {
    "ContainingType": "UniversityManagmentSystem.Controllers.RoomFeatureAllocationController",
    "Method": "GetRoomFeatureAllocation",
    "RelativePath": "RoomFeatureAllocation/Get",
    "HttpMethod": "POST",
    "IsController": true,
    "Order": 0,
    "Parameters": [],
    "ReturnTypes": []
  },
  {
    "ContainingType": "UniversityManagmentSystem.Controllers.RoomFeatureAllocationController",
    "Method": "AddRoomFeatureAllocation",
    "RelativePath": "RoomFeatureAllocation/Post",
    "HttpMethod": "POST",
    "IsController": true,
    "Order": 0,
    "Parameters": [
      {
        "Name": "Id",
        "Type": "System.Int32",
        "IsRequired": false
      },
      {
        "Name": "RoomFeatureId",
        "Type": "System.Int32",
        "IsRequired": false
      },
      {
        "Name": "RoomId",
        "Type": "System.Int32",
        "IsRequired": false
      },
      {
        "Name": "Quantity",
        "Type": "System.Int32",
        "IsRequired": false
      }
    ],
    "ReturnTypes": []
  },
  {
    "ContainingType": "UniversityManagmentSystem.Controllers.RoomTypeController",
    "Method": "RemoveRoomType",
    "RelativePath": "RoomType/Delete",
    "HttpMethod": "POST",
    "IsController": true,
    "Order": 0,
    "Parameters": [
      {
        "Name": "Id",
        "Type": "System.Int32",
        "IsRequired": false
      },
      {
        "Name": "RoomFeatureName",
        "Type": "System.String",
        "IsRequired": false
      },
      {
        "Name": "Code",
        "Type": "System.String",
        "IsRequired": false
      },
      {
        "Name": "Description",
        "Type": "System.String",
        "IsRequired": false
      }
    ],
    "ReturnTypes": []
  },
  {
    "ContainingType": "UniversityManagmentSystem.Controllers.RoomTypeController",
    "Method": "GellAllRoomType",
    "RelativePath": "RoomType/Get",
    "HttpMethod": "GET",
    "IsController": true,
    "Order": 0,
    "Parameters": [],
    "ReturnTypes": []
  },
  {
    "ContainingType": "UniversityManagmentSystem.Controllers.RoomTypeController",
    "Method": "Post",
    "RelativePath": "RoomType/RoomType",
    "HttpMethod": "POST",
    "IsController": true,
    "Order": 0,
    "Parameters": [
      {
        "Name": "Id",
        "Type": "System.Int32",
        "IsRequired": false
      },
      {
        "Name": "RoomTypeName",
        "Type": "System.String",
        "IsRequired": false
      },
      {
        "Name": "Code",
        "Type": "System.String",
        "IsRequired": false
      },
      {
        "Name": "Description",
        "Type": "System.String",
        "IsRequired": false
      }
    ],
    "ReturnTypes": []
  },
  {
    "ContainingType": "UniversityManagmentSystem.Controllers.RoomTypeAllocationController",
    "Method": "Delete",
    "RelativePath": "RoomTypeAllocation/DeleteRoomTypeAllocation",
    "HttpMethod": "POST",
    "IsController": true,
    "Order": 0,
    "Parameters": [
      {
        "Name": "request",
        "Type": "UniversityManagmentSystem.DTOs.RequestDTO.RoomTypeAllocationRequest",
        "IsRequired": true
      }
    ],
    "ReturnTypes": []
  },
  {
    "ContainingType": "UniversityManagmentSystem.Controllers.RoomTypeAllocationController",
    "Method": "GetAllRoomTypeAllocations",
    "RelativePath": "RoomTypeAllocation/Get",
    "HttpMethod": "GET",
    "IsController": true,
    "Order": 0,
    "Parameters": [],
    "ReturnTypes": []
  },
  {
    "ContainingType": "UniversityManagmentSystem.Controllers.RoomTypeAllocationController",
    "Method": "Post",
    "RelativePath": "RoomTypeAllocation/Post",
    "HttpMethod": "POST",
    "IsController": true,
    "Order": 0,
    "Parameters": [
      {
        "Name": "Id",
        "Type": "System.Int32",
        "IsRequired": false
      },
      {
        "Name": "RoomTypeId",
        "Type": "System.Int32",
        "IsRequired": false
      },
      {
        "Name": "RoomId",
        "Type": "System.Int32",
        "IsRequired": false
      }
    ],
    "ReturnTypes": []
  },
  {
    "ContainingType": "UniversityManagmentSystem.Controllers.SemesterController",
    "Method": "RemoveSemester",
    "RelativePath": "Semester/Delete/{Id}",
    "HttpMethod": "POST",
    "IsController": true,
    "Order": 0,
    "Parameters": [
      {
        "Name": "Id",
        "Type": "System.Int32",
        "IsRequired": false
      },
      {
        "Name": "SemesterName",
        "Type": "System.String",
        "IsRequired": false
      },
      {
        "Name": "Code",
        "Type": "System.String",
        "IsRequired": false
      },
      {
        "Name": "Description",
        "Type": "System.String",
        "IsRequired": false
      },
      {
        "Name": "Id",
        "Type": "",
        "IsRequired": true
      }
    ],
    "ReturnTypes": []
  },
  {
    "ContainingType": "UniversityManagmentSystem.Controllers.SemesterController",
    "Method": "Post",
    "RelativePath": "Semester/Semester",
    "HttpMethod": "POST",
    "IsController": true,
    "Order": 0,
    "Parameters": [
      {
        "Name": "Id",
        "Type": "System.Int32",
        "IsRequired": false
      },
      {
        "Name": "SemesterName",
        "Type": "System.String",
        "IsRequired": false
      },
      {
        "Name": "Code",
        "Type": "System.String",
        "IsRequired": false
      },
      {
        "Name": "Description",
        "Type": "System.String",
        "IsRequired": false
      }
    ],
    "ReturnTypes": []
  },
  {
    "ContainingType": "UniversityManagmentSystem.Controllers.SemesterController",
    "Method": "GetAllSemester",
    "RelativePath": "Semester/Semester",
    "HttpMethod": "GET",
    "IsController": true,
    "Order": 0,
    "Parameters": [],
    "ReturnTypes": []
  },
  {
    "ContainingType": "UniversityManagmentSystem.Controllers.StructureDesignationController",
    "Method": "Delete",
    "RelativePath": "StructureDesignation/DeleteStructureDesignation",
    "HttpMethod": "POST",
    "IsController": true,
    "Order": 0,
    "Parameters": [
      {
        "Name": "request",
        "Type": "UniversityManagmentSystem.DTOs.RequestDTO.StructureDesignationRequestDTO",
        "IsRequired": true
      }
    ],
    "ReturnTypes": []
  },
  {
    "ContainingType": "UniversityManagmentSystem.Controllers.StructureDesignationController",
    "Method": "GetAllStructureDesignations",
    "RelativePath": "StructureDesignation/Get",
    "HttpMethod": "GET",
    "IsController": true,
    "Order": 0,
    "Parameters": [],
    "ReturnTypes": []
  },
  {
    "ContainingType": "UniversityManagmentSystem.Controllers.StructureDesignationController",
    "Method": "Post",
    "RelativePath": "StructureDesignation/Post",
    "HttpMethod": "POST",
    "IsController": true,
    "Order": 0,
    "Parameters": [
      {
        "Name": "Id",
        "Type": "System.Int32",
        "IsRequired": false
      },
      {
        "Name": "StructureUnitId",
        "Type": "System.Int32",
        "IsRequired": false
      },
      {
        "Name": "DesignationId",
        "Type": "System.Int32",
        "IsRequired": false
      }
    ],
    "ReturnTypes": []
  },
  {
    "ContainingType": "UniversityManagmentSystem.Controllers.StructureTypeController",
    "Method": "RemoveStructureType",
    "RelativePath": "StructureType/Delete/{Id}",
    "HttpMethod": "POST",
    "IsController": true,
    "Order": 0,
    "Parameters": [
      {
        "Name": "Id",
        "Type": "System.Int32",
        "IsRequired": false
      },
      {
        "Name": "StructureTypeName",
        "Type": "System.String",
        "IsRequired": false
      },
      {
        "Name": "Description",
        "Type": "System.String",
        "IsRequired": false
      },
      {
        "Name": "Code",
        "Type": "System.String",
        "IsRequired": false
      },
      {
        "Name": "Id",
        "Type": "",
        "IsRequired": true
      }
    ],
    "ReturnTypes": []
  },
  {
    "ContainingType": "UniversityManagmentSystem.Controllers.StructureTypeController",
    "Method": "GetAllStructureType",
    "RelativePath": "StructureType/Semester",
    "HttpMethod": "GET",
    "IsController": true,
    "Order": 0,
    "Parameters": [],
    "ReturnTypes": []
  },
  {
    "ContainingType": "UniversityManagmentSystem.Controllers.StructureTypeController",
    "Method": "Post",
    "RelativePath": "StructureType/StructureType",
    "HttpMethod": "POST",
    "IsController": true,
    "Order": 0,
    "Parameters": [
      {
        "Name": "Id",
        "Type": "System.Int32",
        "IsRequired": false
      },
      {
        "Name": "StructureTypeName",
        "Type": "System.String",
        "IsRequired": false
      },
      {
        "Name": "Description",
        "Type": "System.String",
        "IsRequired": false
      },
      {
        "Name": "Code",
        "Type": "System.String",
        "IsRequired": false
      }
    ],
    "ReturnTypes": []
  },
  {
    "ContainingType": "UniversityManagmentSystem.Controllers.SubjectController",
    "Method": "RemoveSubject",
    "RelativePath": "Subject/Delete/{Id}",
    "HttpMethod": "POST",
    "IsController": true,
    "Order": 0,
    "Parameters": [
      {
        "Name": "Id",
        "Type": "System.Int32",
        "IsRequired": false
      },
      {
        "Name": "SubjectName",
        "Type": "System.String",
        "IsRequired": false
      },
      {
        "Name": "Description",
        "Type": "System.String",
        "IsRequired": false
      },
      {
        "Name": "Code",
        "Type": "System.String",
        "IsRequired": false
      },
      {
        "Name": "Id",
        "Type": "",
        "IsRequired": true
      }
    ],
    "ReturnTypes": []
  },
  {
    "ContainingType": "UniversityManagmentSystem.Controllers.SubjectController",
    "Method": "GetAllSubject",
    "RelativePath": "Subject/Semester",
    "HttpMethod": "GET",
    "IsController": true,
    "Order": 0,
    "Parameters": [],
    "ReturnTypes": []
  },
  {
    "ContainingType": "UniversityManagmentSystem.Controllers.SubjectController",
    "Method": "Post",
    "RelativePath": "Subject/Subject",
    "HttpMethod": "POST",
    "IsController": true,
    "Order": 0,
    "Parameters": [
      {
        "Name": "Id",
        "Type": "System.Int32",
        "IsRequired": false
      },
      {
        "Name": "SubjectName",
        "Type": "System.String",
        "IsRequired": false
      },
      {
        "Name": "Description",
        "Type": "System.String",
        "IsRequired": false
      },
      {
        "Name": "Code",
        "Type": "System.String",
        "IsRequired": false
      }
    ],
    "ReturnTypes": []
  },
  {
    "ContainingType": "UniversityManagmentSystem.Controllers.SubjectTypeController",
    "Method": "RemoveSubjectType",
    "RelativePath": "SubjectType/Delete/{Id}",
    "HttpMethod": "POST",
    "IsController": true,
    "Order": 0,
    "Parameters": [
      {
        "Name": "Id",
        "Type": "System.Int32",
        "IsRequired": false
      },
      {
        "Name": "SubjectName",
        "Type": "System.String",
        "IsRequired": false
      },
      {
        "Name": "Description",
        "Type": "System.String",
        "IsRequired": false
      },
      {
        "Name": "Code",
        "Type": "System.String",
        "IsRequired": false
      },
      {
        "Name": "Id",
        "Type": "",
        "IsRequired": true
      }
    ],
    "ReturnTypes": []
  },
  {
    "ContainingType": "UniversityManagmentSystem.Controllers.SubjectTypeController",
    "Method": "GetAllSubjectType",
    "RelativePath": "SubjectType/Semester",
    "HttpMethod": "GET",
    "IsController": true,
    "Order": 0,
    "Parameters": [],
    "ReturnTypes": []
  },
  {
    "ContainingType": "UniversityManagmentSystem.Controllers.SubjectTypeController",
    "Method": "Post",
    "RelativePath": "SubjectType/SubjectType",
    "HttpMethod": "POST",
    "IsController": true,
    "Order": 0,
    "Parameters": [
      {
        "Name": "Id",
        "Type": "System.Int32",
        "IsRequired": false
      },
      {
        "Name": "TypeName",
        "Type": "System.String",
        "IsRequired": false
      },
      {
        "Name": "Description",
        "Type": "System.String",
        "IsRequired": false
      },
      {
        "Name": "Code",
        "Type": "System.String",
        "IsRequired": false
      }
    ],
    "ReturnTypes": []
  },
  {
    "ContainingType": "UniversityManagmentSystem.Controllers.UniController",
    "Method": "Post",
    "RelativePath": "Uni",
    "HttpMethod": "POST",
    "IsController": true,
    "Order": 0,
    "Parameters": [
      {
        "Name": "UniversityName",
        "Type": "System.String",
        "IsRequired": false
      },
      {
        "Name": "Description",
        "Type": "System.String",
        "IsRequired": false
      },
      {
        "Name": "EstablishedIn",
        "Type": "System.DateTime",
        "IsRequired": false
      },
      {
        "Name": "Address",
        "Type": "System.String",
        "IsRequired": false
      },
      {
        "Name": "Campuses",
        "Type": "System.Collections.Generic.List\u00601[[UniversityManagmentSystem.Models.Campus, UniversityManagmentSystem, Version=1.0.0.0, Culture=neutral, PublicKeyToken=null]]",
        "IsRequired": false
      },
      {
        "Name": "Id",
        "Type": "System.Int32",
        "IsRequired": false
      },
      {
        "Name": "IsActive",
        "Type": "System.Boolean",
        "IsRequired": false
      },
      {
        "Name": "GlobalId",
        "Type": "System.Guid",
        "IsRequired": false
      },
      {
        "Name": "CreatedAt",
        "Type": "System.DateTime",
        "IsRequired": false
      },
      {
        "Name": "UpdatedAt",
        "Type": "System.DateTime",
        "IsRequired": false
      },
      {
        "Name": "DeletedAt",
        "Type": "System.DateTime",
        "IsRequired": false
      },
      {
        "Name": "CreatedBy",
        "Type": "System.Int32",
        "IsRequired": false
      },
      {
        "Name": "UpdatedBy",
        "Type": "System.Int32",
        "IsRequired": false
      },
      {
        "Name": "DeletedBy",
        "Type": "System.Int32",
        "IsRequired": false
      }
    ],
    "ReturnTypes": []
  },
  {
    "ContainingType": "UniversityManagmentSystem.Controllers.UniversityController",
    "Method": "Post",
    "RelativePath": "University",
    "HttpMethod": "POST",
    "IsController": true,
    "Order": 0,
    "Parameters": [
      {
        "Name": "request",
        "Type": "UniversityManagmentSystem.DTOs.RequestDTO.UniversityRequestDTO",
        "IsRequired": true
      }
    ],
    "ReturnTypes": []
  },
  {
    "ContainingType": "UniversityManagmentSystem.Controllers.UniversityController",
    "Method": "Delete",
    "RelativePath": "University/DeleteUniversity",
    "HttpMethod": "POST",
    "IsController": true,
    "Order": 0,
    "Parameters": [
      {
        "Name": "request",
        "Type": "UniversityManagmentSystem.DTOs.RequestDTO.UniversityRequestDTO",
        "IsRequired": true
      }
    ],
    "ReturnTypes": []
  },
  {
    "ContainingType": "UniversityManagmentSystem.Controllers.UniversityController",
    "Method": "GetAllUniversities",
    "RelativePath": "University/Get",
    "HttpMethod": "GET",
    "IsController": true,
    "Order": 0,
    "Parameters": [],
    "ReturnTypes": []
  },
  {
    "ContainingType": "UniversityManagmentSystem.Controllers.UserInfoController",
    "Method": "Post",
    "RelativePath": "UserInfo",
    "HttpMethod": "POST",
    "IsController": true,
    "Order": 0,
    "Parameters": [
      {
        "Name": "request",
        "Type": "UniversityManagmentSystem.DTOs.RequestDTO.UserInfoRequestDTO",
        "IsRequired": true
      }
    ],
    "ReturnTypes": []
  },
  {
    "ContainingType": "UniversityManagmentSystem.Controllers.UserInfoController",
    "Method": "Delete",
    "RelativePath": "UserInfo/DeleteUserInfo",
    "HttpMethod": "POST",
    "IsController": true,
    "Order": 0,
    "Parameters": [
      {
        "Name": "request",
        "Type": "UniversityManagmentSystem.DTOs.RequestDTO.UserInfoRequestDTO",
        "IsRequired": true
      }
    ],
    "ReturnTypes": []
  },
  {
    "ContainingType": "UniversityManagmentSystem.Controllers.UserInfoController",
    "Method": "GetAllUserInfos",
    "RelativePath": "UserInfo/Get",
    "HttpMethod": "GET",
    "IsController": true,
    "Order": 0,
    "Parameters": [],
    "ReturnTypes": []
  },
  {
    "ContainingType": "UniversityManagmentSystem.Controllers.UserRightController",
    "Method": "Post",
    "RelativePath": "UserRight",
    "HttpMethod": "POST",
    "IsController": true,
    "Order": 0,
    "Parameters": [
      {
        "Name": "request",
        "Type": "UniversityManagmentSystem.DTOs.RequestDTO.UserRightRequestDTO",
        "IsRequired": true
      }
    ],
    "ReturnTypes": []
  },
  {
    "ContainingType": "UniversityManagmentSystem.Controllers.UserRightController",
    "Method": "Delete",
    "RelativePath": "UserRight/DeleteUserRight",
    "HttpMethod": "POST",
    "IsController": true,
    "Order": 0,
    "Parameters": [
      {
        "Name": "request",
        "Type": "UniversityManagmentSystem.DTOs.RequestDTO.UserRightRequestDTO",
        "IsRequired": true
      }
    ],
    "ReturnTypes": []
  },
  {
    "ContainingType": "UniversityManagmentSystem.Controllers.UserRightController",
    "Method": "GetAllUserRights",
    "RelativePath": "UserRight/Get",
    "HttpMethod": "GET",
    "IsController": true,
    "Order": 0,
    "Parameters": [],
    "ReturnTypes": []
  },
  {
    "ContainingType": "UniversityManagmentSystem.Controllers.UserRightAllocationController",
    "Method": "Post",
    "RelativePath": "UserRightAllocation",
    "HttpMethod": "POST",
    "IsController": true,
    "Order": 0,
    "Parameters": [
      {
        "Name": "request",
        "Type": "UniversityManagmentSystem.DTOs.RequestDTO.UserRightAllocationRequestDTO",
        "IsRequired": true
      }
    ],
    "ReturnTypes": []
  },
  {
    "ContainingType": "UniversityManagmentSystem.Controllers.UserRightAllocationController",
    "Method": "Delete",
    "RelativePath": "UserRightAllocation/DeleteUserRight",
    "HttpMethod": "POST",
    "IsController": true,
    "Order": 0,
    "Parameters": [
      {
        "Name": "request",
        "Type": "UniversityManagmentSystem.DTOs.RequestDTO.UserRightAllocationRequestDTO",
        "IsRequired": true
      }
    ],
    "ReturnTypes": []
  },
  {
    "ContainingType": "UniversityManagmentSystem.Controllers.UserRightAllocationController",
    "Method": "GetAllUserRights",
    "RelativePath": "UserRightAllocation/Get",
    "HttpMethod": "GET",
    "IsController": true,
    "Order": 0,
    "Parameters": [],
    "ReturnTypes": []
  },
  {
    "ContainingType": "UniversityManagmentSystem.Controllers.UserTypeController",
    "Method": "Post",
    "RelativePath": "UserType",
    "HttpMethod": "POST",
    "IsController": true,
    "Order": 0,
    "Parameters": [
      {
        "Name": "request",
        "Type": "UniversityManagmentSystem.DTOs.RequestDTO.UserTypeRequestDTO",
        "IsRequired": true
      }
    ],
    "ReturnTypes": []
  },
  {
    "ContainingType": "UniversityManagmentSystem.Controllers.UserTypeController",
    "Method": "Delete",
    "RelativePath": "UserType/DeleteUserType",
    "HttpMethod": "POST",
    "IsController": true,
    "Order": 0,
    "Parameters": [
      {
        "Name": "request",
        "Type": "UniversityManagmentSystem.DTOs.RequestDTO.UserTypeRequestDTO",
        "IsRequired": true
      }
    ],
    "ReturnTypes": []
  },
  {
    "ContainingType": "UniversityManagmentSystem.Controllers.UserTypeController",
    "Method": "GetAllUserTypes",
    "RelativePath": "UserType/Get",
    "HttpMethod": "GET",
    "IsController": true,
    "Order": 0,
    "Parameters": [],
    "ReturnTypes": []
  },
  {
    "ContainingType": "UniversityManagmentSystem.Controllers.UserTypeAllocationController",
    "Method": "Post",
    "RelativePath": "UserTypeAllocation",
    "HttpMethod": "POST",
    "IsController": true,
    "Order": 0,
    "Parameters": [
      {
        "Name": "request",
        "Type": "UniversityManagmentSystem.DTOs.RequestDTO.UserTypeAllocationRequestDTO",
        "IsRequired": true
      }
    ],
    "ReturnTypes": []
  },
  {
    "ContainingType": "UniversityManagmentSystem.Controllers.UserTypeAllocationController",
    "Method": "Delete",
    "RelativePath": "UserTypeAllocation/DeleteUserType",
    "HttpMethod": "POST",
    "IsController": true,
    "Order": 0,
    "Parameters": [
      {
        "Name": "request",
        "Type": "UniversityManagmentSystem.DTOs.RequestDTO.UserTypeAllocationRequestDTO",
        "IsRequired": true
      }
    ],
    "ReturnTypes": []
  },
  {
    "ContainingType": "UniversityManagmentSystem.Controllers.UserTypeAllocationController",
    "Method": "GetAllUserTypes",
    "RelativePath": "UserTypeAllocation/Get",
    "HttpMethod": "GET",
    "IsController": true,
    "Order": 0,
    "Parameters": [],
    "ReturnTypes": []
  }
]